rustitude-0.10.3.dist-info/METADATA
rustitude-0.10.3.dist-info/WHEEL
rustitude-0.10.3.dist-info/license_files/LICENSE
rustitude/__init__.pyi
rustitude/gluex/polarization.pyi
rustitude/gluex/__init__.pyi
rustitude/gluex/sdmes.pyi
rustitude/gluex/harmonics.pyi
rustitude/gluex/resonances.pyi
rustitude/gluex/dalitz.pyi
rustitude/py.typed
rustitude/__init__.py
rustitude/_rustitude.abi3.so
rustitude-0.10.3.dist-info/RECORD
