Metadata-Version: 2.3
Name: rustitude
Version: 0.10.3
Classifier: Development Status :: 4 - Beta
Classifier: Programming Language :: Python
Requires-Dist: uproot
Requires-Dist: numpy
Requires-Dist: iminuit
Requires-Dist: scipy >=1.14
License-File: LICENSE
Summary: Python bindings for the Rustitude library
Keywords: physics,math,rust
Author: Nathaniel Dene Hoffman
Author-email: dene@cmu.edu
Maintainer-email: Nathaniel Dene Hoffman <dene@cmu.edu>
Requires-Python: >=3.7
Project-URL: homepage, https://github.com/denehoffman/rustitude
Project-URL: repository, https://github.com/denehoffman/rustitude
Project-URL: changelog, https://github.com/denehoffman/rustitude/blob/main/CHANGELOG.md
Project-URL: documentation, https://rustitude.readthedocs.io/en/latest/
